flexprofiler/__init__.py
flexprofiler/default_profiler.py
flexprofiler/profiler.py
flexprofiler-0.1.5.dist-info/METADATA
flexprofiler-0.1.5.dist-info/WHEEL
flexprofiler-0.1.5.dist-info/licenses/LICENSE
flexprofiler-0.1.5.dist-info/RECORD
