Metadata-Version: 2.4
Name: flexprofiler
Version: 0.1.5
Summary: A flexible profiling utility for Python.
Author-email: Arthur Bucker <abucker@andrew.cmu.edu>
License: MIT License
License-File: LICENSE
Classifier: License :: OSI Approved :: MIT License
Classifier: Operating System :: OS Independent
Classifier: Programming Language :: Python :: 3
Requires-Python: >=3.7
